{"global": [["used", 80], ["entity", 59], ["activity", 53], ["wasGeneratedBy", 53], ["accessedPart", 31], ["wasDerivedFrom", 26], ["value", 20], ["defined", 14], ["wasDefinedBy", 14], ["accessed", 14], ["derivedByInsertion", 5]], "1": [["entity", 2], ["value", 1], ["defined", 1], ["wasDefinedBy", 1], ["activity", 1], ["used", 1], ["wasDerivedFrom", 1], ["wasGeneratedBy", 1], ["accessed", 1]], "2": [["value", 8], ["entity", 7], ["defined", 5], ["wasDefinedBy", 5], ["derivedByInsertion", 4], ["accessed", 2], ["activity", 2], ["used", 2], ["wasDerivedFrom", 2], ["wasGeneratedBy", 2]], "7": [["entity", 2], ["activity", 2], ["used", 2], ["wasGeneratedBy", 2], ["value", 1], ["defined", 1], ["wasDefinedBy", 1], ["accessed", 1], ["wasDerivedFrom", 1]], "8": [["value", 4], ["entity", 2], ["activity", 2], ["used", 2], ["wasGeneratedBy", 2], ["derivedByInsertion", 1], ["defined", 1], ["wasDefinedBy", 1], ["accessed", 1], ["wasDerivedFrom", 1]], "9": [["entity", 1], ["accessedPart", 1], ["activity", 1], ["used", 1], ["wasGeneratedBy", 1]], "10": [["used", 3], ["entity", 2], ["activity", 2], ["wasGeneratedBy", 2], ["accessedPart", 1], ["accessed", 1], ["wasDerivedFrom", 1]], "11": [["entity", 3], ["accessedPart", 3], ["activity", 3], ["used", 3], ["wasGeneratedBy", 3]], "12": [["used", 6], ["entity", 4], ["activity", 4], ["wasGeneratedBy", 4], ["accessedPart", 2], ["accessed", 2], ["wasDerivedFrom", 2]], "13": [["entity", 6], ["accessedPart", 6], ["activity", 6], ["used", 6], ["wasGeneratedBy", 6]], "14": [["used", 42], ["entity", 24], ["activity", 24], ["wasGeneratedBy", 24], ["wasDerivedFrom", 18], ["accessedPart", 12], ["value", 6], ["defined", 6], ["wasDefinedBy", 6], ["accessed", 6]], "15": [["used", 12], ["entity", 6], ["accessedPart", 6], ["activity", 6], ["wasGeneratedBy", 6]]}