{"global": [["used", 288], ["entity", 188], ["activity", 182], ["wasGeneratedBy", 182], ["accessedPart", 115], ["wasDerivedFrom", 88], ["accessed", 42], ["value", 37], ["defined", 31], ["wasDefinedBy", 31], ["derivedByInsertion", 8]], "1": [["entity", 2], ["value", 1], ["defined", 1], ["wasDefinedBy", 1], ["activity", 1], ["used", 1], ["wasDerivedFrom", 1], ["wasGeneratedBy", 1], ["accessed", 1]], "2": [["value", 8], ["entity", 7], ["defined", 5], ["wasDefinedBy", 5], ["derivedByInsertion", 4], ["accessed", 2], ["activity", 2], ["used", 2], ["wasDerivedFrom", 2], ["wasGeneratedBy", 2]], "7": [["entity", 2], ["activity", 2], ["used", 2], ["wasGeneratedBy", 2], ["value", 1], ["defined", 1], ["wasDefinedBy", 1], ["accessed", 1], ["wasDerivedFrom", 1]], "8": [["value", 4], ["entity", 2], ["activity", 2], ["used", 2], ["wasGeneratedBy", 2], ["derivedByInsertion", 1], ["defined", 1], ["wasDefinedBy", 1], ["accessed", 1], ["wasDerivedFrom", 1]], "9": [["entity", 3], ["accessedPart", 3], ["activity", 3], ["used", 3], ["wasGeneratedBy", 3]], "10": [["used", 9], ["entity", 6], ["activity", 6], ["wasGeneratedBy", 6], ["accessedPart", 3], ["accessed", 3], ["wasDerivedFrom", 3]], "11": [["entity", 8], ["accessedPart", 8], ["activity", 8], ["used", 8], ["wasGeneratedBy", 8]], "12": [["used", 24], ["entity", 16], ["activity", 16], ["wasGeneratedBy", 16], ["accessedPart", 8], ["accessed", 8], ["wasDerivedFrom", 8]], "13": [["entity", 24], ["accessedPart", 24], ["activity", 24], ["used", 24], ["wasGeneratedBy", 24]], "14": [["used", 161], ["entity", 92], ["activity", 92], ["wasGeneratedBy", 92], ["wasDerivedFrom", 69], ["accessedPart", 46], ["value", 23], ["defined", 23], ["wasDefinedBy", 23], ["accessed", 23]], "15": [["used", 46], ["entity", 23], ["accessedPart", 23], ["activity", 23], ["wasGeneratedBy", 23]], "16": [["used", 6], ["entity", 3], ["derivedByInsertion", 3], ["accessed", 3], ["activity", 3], ["wasDerivedFrom", 3], ["wasGeneratedBy", 3]]}