{"all": {"lines": [[17, 10], [18, 9], [14, 4], [15, 4], [16, 4], [19, 4], [20, 4], [12, 2], [13, 2], [2, 1], [3, 1], [4, 1], [10, 1], [11, 1], [21, 1]], "global": [["entity", 88], ["wasDerivedFrom", 59], ["used", 58], ["activity", 57], ["specializationOf", 19], ["hadDictionaryMember", 15], ["wasGeneratedBy", 2], ["derivedByInsertionFrom", 1]], "2": [["entity", 3], ["specializationOf", 1], ["activity", 1], ["wasDerivedFrom", 1]], "3": [["entity", 7], ["specializationOf", 3], ["hadDictionaryMember", 3], ["activity", 1], ["wasDerivedFrom", 1]], "4": [["entity", 12], ["hadDictionaryMember", 9], ["specializationOf", 5], ["activity", 2], ["wasDerivedFrom", 2]], "10": [["entity", 3], ["activity", 2], ["specializationOf", 1], ["used", 1], ["wasGeneratedBy", 1], ["wasDerivedFrom", 1]], "11": [["entity", 9], ["specializationOf", 4], ["hadDictionaryMember", 3], ["activity", 2], ["used", 1], ["wasGeneratedBy", 1], ["wasDerivedFrom", 1]], "12": [["entity", 2], ["activity", 2], ["wasDerivedFrom", 2], ["used", 2]], "13": [["entity", 4], ["activity", 4], ["wasDerivedFrom", 4], ["used", 4]], "14": [["entity", 4], ["activity", 4], ["wasDerivedFrom", 4], ["used", 4]], "16": [["entity", 8], ["activity", 8], ["wasDerivedFrom", 8], ["used", 8]], "17": [["entity", 10], ["activity", 10], ["wasDerivedFrom", 10], ["used", 10]], "19": [["entity", 20], ["wasDerivedFrom", 20], ["activity", 16], ["used", 16], ["specializationOf", 4]], "20": [["used", 8], ["entity", 4], ["activity", 4], ["wasDerivedFrom", 4]], "21": [["used", 4], ["entity", 2], ["derivedByInsertionFrom", 1], ["specializationOf", 1], ["activity", 1], ["wasDerivedFrom", 1]]}, "visible": {"global": [["entity", 53], ["specializationOf", 19], ["hadDictionaryMember", 15], ["used", 4], ["derivedByInsertionFrom", 1], ["activity", 1], ["wasDerivedFrom", 1]], "2": [["entity", 2], ["specializationOf", 1]], "3": [["entity", 7], ["specializationOf", 3], ["hadDictionaryMember", 3]], "4": [["entity", 12], ["hadDictionaryMember", 9], ["specializationOf", 5]], "10": [["entity", 1], ["specializationOf", 1]], "11": [["entity", 9], ["specializationOf", 4], ["hadDictionaryMember", 3]], "13": [["entity", 4]], "16": [["entity", 8]], "19": [["entity", 8], ["specializationOf", 4]], "21": [["used", 4], ["entity", 2], ["derivedByInsertionFrom", 1], ["specializationOf", 1], ["activity", 1], ["wasDerivedFrom", 1]]}, "specific": {"global": [["entity", 19], ["specializationOf", 19], ["hadDictionaryMember", 15], ["derivedByInsertionFrom", 1], ["used", 1]], "2": [["entity", 1], ["specializationOf", 1]], "3": [["entity", 3], ["specializationOf", 3], ["hadDictionaryMember", 3]], "4": [["hadDictionaryMember", 9], ["entity", 5], ["specializationOf", 5]], "10": [["entity", 1], ["specializationOf", 1]], "11": [["entity", 4], ["specializationOf", 4], ["hadDictionaryMember", 3]], "19": [["entity", 4], ["specializationOf", 4]], "21": [["entity", 1], ["derivedByInsertionFrom", 1], ["specializationOf", 1], ["used", 1]]}}