{"all": {"lines": [[13, 18], [14, 17], [10, 8], [11, 8], [12, 6], [15, 6], [16, 6], [8, 3], [9, 3], [17, 3], [1, 1], [2, 1], [6, 1], [7, 1]], "global": [["entity", 93], ["used", 88], ["activity", 87], ["wasGeneratedBy", 58], ["accessedPart", 56], ["wasDerivedFrom", 35], ["accessed", 23], ["value", 20], ["defined", 14], ["wasDefinedBy", 14], ["derivedByInsertion", 8]], "1": [["entity", 2], ["value", 1], ["defined", 1], ["wasDefinedBy", 1], ["activity", 1], ["wasDerivedFrom", 1], ["accessed", 1]], "2": [["value", 8], ["entity", 7], ["defined", 5], ["wasDefinedBy", 5], ["derivedByInsertion", 4], ["accessed", 2], ["activity", 2], ["wasDerivedFrom", 2]], "6": [["entity", 2], ["activity", 2], ["value", 1], ["defined", 1], ["wasDefinedBy", 1], ["used", 1], ["wasGeneratedBy", 1], ["accessed", 1], ["wasDerivedFrom", 1]], "7": [["value", 4], ["entity", 2], ["activity", 2], ["derivedByInsertion", 1], ["defined", 1], ["wasDefinedBy", 1], ["used", 1], ["wasGeneratedBy", 1], ["accessed", 1], ["wasDerivedFrom", 1]], "8": [["entity", 3], ["accessedPart", 3], ["activity", 3], ["used", 3], ["wasGeneratedBy", 3]], "9": [["entity", 6], ["activity", 6], ["used", 6], ["accessedPart", 3], ["wasGeneratedBy", 3], ["accessed", 3], ["wasDerivedFrom", 3]], "10": [["entity", 8], ["accessedPart", 8], ["activity", 8], ["used", 8], ["wasGeneratedBy", 8]], "12": [["entity", 12], ["activity", 12], ["used", 12], ["accessedPart", 6], ["wasGeneratedBy", 6], ["accessed", 6], ["wasDerivedFrom", 6]], "13": [["entity", 18], ["accessedPart", 18], ["activity", 18], ["used", 18], ["wasGeneratedBy", 18]], "15": [["entity", 24], ["activity", 24], ["used", 24], ["wasDerivedFrom", 18], ["accessedPart", 12], ["wasGeneratedBy", 12], ["value", 6], ["defined", 6], ["wasDefinedBy", 6], ["accessed", 6]], "16": [["used", 12], ["entity", 6], ["accessedPart", 6], ["activity", 6], ["wasGeneratedBy", 6]], "17": [["entity", 3], ["derivedByInsertion", 3], ["accessed", 3], ["activity", 3], ["wasDerivedFrom", 3], ["used", 3]]}, "visible": {"global": [["accessedPart", 56], ["entity", 28], ["accessed", 23], ["value", 20], ["defined", 14], ["wasDefinedBy", 14], ["derivedByInsertion", 8], ["activity", 3], ["wasDerivedFrom", 3], ["used", 3]], "1": [["value", 1], ["defined", 1], ["wasDefinedBy", 1], ["accessed", 1]], "2": [["value", 8], ["defined", 5], ["wasDefinedBy", 5], ["derivedByInsertion", 4], ["entity", 3], ["accessed", 2]], "6": [["entity", 2], ["value", 1], ["defined", 1], ["wasDefinedBy", 1], ["accessed", 1]], "7": [["value", 4], ["entity", 2], ["derivedByInsertion", 1], ["defined", 1], ["wasDefinedBy", 1], ["accessed", 1]], "8": [["accessedPart", 3]], "9": [["entity", 6], ["accessedPart", 3], ["accessed", 3]], "10": [["accessedPart", 8]], "12": [["entity", 12], ["accessedPart", 6], ["accessed", 6]], "13": [["accessedPart", 18]], "15": [["accessedPart", 12], ["value", 6], ["defined", 6], ["wasDefinedBy", 6], ["accessed", 6]], "16": [["accessedPart", 6]], "17": [["entity", 3], ["derivedByInsertion", 3], ["accessed", 3], ["activity", 3], ["wasDerivedFrom", 3], ["used", 3]]}, "specific": {"global": [["accessedPart", 56], ["accessed", 23], ["value", 20], ["defined", 14], ["wasDefinedBy", 14], ["derivedByInsertion", 8]], "1": [["value", 1], ["defined", 1], ["wasDefinedBy", 1], ["accessed", 1]], "2": [["value", 8], ["defined", 5], ["wasDefinedBy", 5], ["derivedByInsertion", 4], ["accessed", 2]], "6": [["value", 1], ["defined", 1], ["wasDefinedBy", 1], ["accessed", 1]], "7": [["value", 4], ["derivedByInsertion", 1], ["defined", 1], ["wasDefinedBy", 1], ["accessed", 1]], "8": [["accessedPart", 3]], "9": [["accessedPart", 3], ["accessed", 3]], "10": [["accessedPart", 8]], "12": [["accessedPart", 6], ["accessed", 6]], "13": [["accessedPart", 18]], "15": [["accessedPart", 12], ["value", 6], ["defined", 6], ["wasDefinedBy", 6], ["accessed", 6]], "16": [["accessedPart", 6]], "17": [["derivedByInsertion", 3], ["accessed", 3]]}}